pysimmods/__init__.py
pysimmods/buffer/__init__.py
pysimmods/buffer/batterysim/__init__.py
pysimmods/buffer/batterysim/battery.py
pysimmods/buffer/batterysim/config.py
pysimmods/buffer/batterysim/inputs.py
pysimmods/buffer/batterysim/presets.py
pysimmods/buffer/batterysim/state.py
pysimmods/consumer/__init__.py
pysimmods/consumer/hvacsim/__init__.py
pysimmods/consumer/hvacsim/config.py
pysimmods/consumer/hvacsim/hvac.py
pysimmods/consumer/hvacsim/inputs.py
pysimmods/consumer/hvacsim/presets.py
pysimmods/consumer/hvacsim/state.py
pysimmods/generator/__init__.py
pysimmods/generator/biogassim/__init__.py
pysimmods/generator/biogassim/biogas.py
pysimmods/generator/biogassim/config.py
pysimmods/generator/biogassim/inputs.py
pysimmods/generator/biogassim/presets.py
pysimmods/generator/biogassim/state.py
pysimmods/generator/chpcngsim/__init__.py
pysimmods/generator/chpcngsim/chpcng.py
pysimmods/generator/chpcngsim/config.py
pysimmods/generator/chpcngsim/inputs.py
pysimmods/generator/chpcngsim/state.py
pysimmods/generator/chplpgsim/__init__.py
pysimmods/generator/chplpgsim/chplpg.py
pysimmods/generator/chplpgsim/config.py
pysimmods/generator/chplpgsim/inputs.py
pysimmods/generator/chplpgsim/state.py
pysimmods/generator/chplpgsystemsim/__init__.py
pysimmods/generator/chplpgsystemsim/chplpg_system.py
pysimmods/generator/chplpgsystemsim/config.py
pysimmods/generator/chplpgsystemsim/inputs.py
pysimmods/generator/chplpgsystemsim/presets.py
pysimmods/generator/chplpgsystemsim/state.py
pysimmods/generator/dieselsim/__init__.py
pysimmods/generator/dieselsim/config.py
pysimmods/generator/dieselsim/dieselgen.py
pysimmods/generator/dieselsim/inputs.py
pysimmods/generator/dieselsim/presets.py
pysimmods/generator/dieselsim/state.py
pysimmods/generator/pvsim/__init__.py
pysimmods/generator/pvsim/config.py
pysimmods/generator/pvsim/inputs.py
pysimmods/generator/pvsim/pvp.py
pysimmods/generator/pvsim/state.py
pysimmods/generator/pvsystemsim/__init__.py
pysimmods-0.20.5.dist-info/licenses/LICENSE
pysimmods-0.20.5.dist-info/METADATA
pysimmods-0.20.5.dist-info/WHEEL
pysimmods-0.20.5.dist-info/top_level.txt
pysimmods-0.20.5.dist-info/RECORD
