Metadata-Version: 2.4
Name: pysimmods
Version: 0.20.5
Summary: A set of simulation models representing different distributed consumer or generator units.
Author-email: Stephan Balduin <stephan.balduin@offis.de>
Project-URL: Homepage, https://midas-mosaik.gitlab.io/pysimmods
Project-URL: Bug Tracker, https://gitlab.com/midas-mosaik/pysimmods/-/issues
Requires-Python: >=3.8
License-File: LICENSE
Requires-Dist: mosaik_api
Requires-Dist: midas-mosaik>=2.0.0
Requires-Dist: pandas
Requires-Dist: numpy<2
Provides-Extra: dev
Requires-Dist: pytest; extra == "dev"
Requires-Dist: build; extra == "dev"
Requires-Dist: flake8; extra == "dev"
Requires-Dist: twine; extra == "dev"
Requires-Dist: black==22.3.0; extra == "dev"
Requires-Dist: coverage; extra == "dev"
Requires-Dist: sphinx; extra == "dev"
Requires-Dist: pytest-cov; extra == "dev"
Requires-Dist: matplotlib; extra == "dev"
Requires-Dist: wheel; extra == "dev"
Dynamic: license-file
